MANIFEST.in
README.rst
ez_setup.py
setup.py
wallp/__init__.py
wallp/__main__.py
wallp/const.py
wallp/main.py
wallp/version.py
wallp/wallpaper.py
wallp.egg-info/PKG-INFO
wallp.egg-info/SOURCES.txt
wallp.egg-info/dependency_links.txt
wallp.egg-info/entry_points.txt
wallp.egg-info/requires.txt
wallp.egg-info/top_level.txt
wallp/db/__init__.py
wallp/db/dbsession.py
wallp/db/app/__init__.py
wallp/db/app/config.py
wallp/db/app/images.py
wallp/db/app/imgur_album_list.py
wallp/db/app/itemlist.py
wallp/db/app/kvhelper.py
wallp/db/app/kvstore.py
wallp/db/app/query_list.py
wallp/db/app/search_page.py
wallp/db/app/sources.py
wallp/db/app/statistics.py
wallp/db/app/subreddit_list.py
wallp/db/app/vars.py
wallp/db/manage/__init__.py
wallp/db/manage/alembic.ini
wallp/db/manage/db.py
wallp/db/manage/data/config2.csv
wallp/db/manage/data/imgur_album.csv
wallp/db/manage/data/query.csv
wallp/db/manage/data/source.csv
wallp/db/manage/data/subreddit.csv
wallp/db/manage/data/var.csv
wallp/db/manage/migrate/__init__.py
wallp/db/manage/migrate/env.py
wallp/db/manage/migrate/versions/25eef620cf9e_add_table_search_page_num.py
wallp/db/manage/migrate/versions/262448a26c0c_search_term_to_query.py
wallp/db/manage/migrate/versions/2c8e87e9d8f3_db_refactor.py
wallp/db/manage/migrate/versions/3eaa788c373b_first_version.py
wallp/db/manage/migrate/versions/75b54db3960d_table_image_add_column_favorite.py
wallp/db/manage/migrate/versions/__init__.py
wallp/db/model/__init__.py
wallp/db/model/all.py
wallp/db/model/base.py
wallp/db/model/config.py
wallp/db/model/image.py
wallp/db/model/image_trace.py
wallp/db/model/imgur_album.py
wallp/db/model/query.py
wallp/db/model/search_page_num.py
wallp/db/model/source.py
wallp/db/model/subreddit.py
wallp/db/model/var.py
wallp/desktop/__init__.py
wallp/desktop/desktop.py
wallp/desktop/desktop_factory.py
wallp/desktop/gnome_desktop.py
wallp/desktop/kde_plasma_desktop.py
wallp/desktop/linux_desktop_helper.py
wallp/desktop/standard_desktop_sizes.py
wallp/desktop/windows_desktop.py
wallp/desktop/wpstyle.py
wallp/server/__init__.py
wallp/server/change_wallpaper.py
wallp/server/scheduler.py
wallp/server/wallp_server.py
